Metadata-Version: 2.1
Name: pythonImageConverter
Version: 1.0.7.2
Summary: Convert image types using CLI
Home-page: http://github.com/Johntheprogrammer92/pythonImageConverter
Author: http://github.com/Johntheprogrammer92
License: MIT
Platform: UNKNOWN
